etc/bash_completion.d/otpme
etc/otpme/otpme.conf.dist
etc/otpme/deploy/pam/README
etc/otpme/deploy/pam/otpme-account
etc/otpme/deploy/pam/otpme-auth
etc/otpme/deploy/pam/otpme-session
etc/otpme/deploy/pam/pam-python/README
etc/otpme/deploy/pam/pam-python/pam_otpme.py
etc/otpme/dicts/abbreviations-it.gz
etc/otpme/dicts/at-surnames.gz
etc/otpme/dicts/common-passwords.gz
etc/otpme/dicts/convert_dict.sh
etc/otpme/dicts/de-female.gz
etc/otpme/dicts/de-male.gz
etc/otpme/dicts/de-surnames.gz
etc/otpme/dicts/de-top10000.gz
etc/otpme/dicts/en-top10000.gz
etc/otpme/dicts/english-guessing.gz
etc/otpme/dicts/english.gz
etc/otpme/dicts/german-guessing.gz
etc/otpme/dicts/german.gz
etc/otpme/dicts/us-female.gz
etc/otpme/dicts/us-male.gz
etc/otpme/dicts/us-surnames.gz
etc/otpme/schema/core.schema
etc/otpme/schema/cosine.schema
etc/otpme/schema/inetorgperson.schema
etc/otpme/schema/misc.schema
etc/otpme/schema/nis.schema
etc/otpme/scripts/agent_script.sh
etc/otpme/scripts/auth_script.sh
etc/otpme/scripts/key_script.sh
etc/otpme/scripts/login_script.sh
etc/otpme/scripts/node_vote_script.sh
etc/otpme/scripts/push_script.sh
otpme/__init__.py
otpme/command.py
otpme/lib/__init__.py
otpme/lib/arp.py
otpme/lib/audit.py
otpme/lib/auth_cache.py
otpme/lib/auth_script.py
otpme/lib/backend.py
otpme/lib/backup.py
otpme/lib/compgen.py
otpme/lib/connections.py
otpme/lib/db_dict.py
otpme/lib/debug.py
otpme/lib/doc.py
otpme/lib/exceptions.py
otpme/lib/filetools.py
otpme/lib/fscoding.py
otpme/lib/fuse.py
otpme/lib/host.py
otpme/lib/incremental_objects.py
otpme/lib/join.py
otpme/lib/json.py
otpme/lib/jwt.py
otpme/lib/locking.py
otpme/lib/log.py
otpme/lib/messages.py
otpme/lib/mschap.py
otpme/lib/mschap_util.py
otpme/lib/multiprocessing.py
otpme/lib/net.py
otpme/lib/nsscache.py
otpme/lib/offline_token.py
otpme/lib/oid.py
otpme/lib/otpme_acl.py
otpme/lib/otpme_config.py
otpme/lib/otpme_pass.py
otpme/lib/pam.py
otpme/lib/pickle.py
otpme/lib/pidfile.py
otpme/lib/preload.py
otpme/lib/progress.py
otpme-0.3.0a151.dist-info/licenses/LICENSE
otpme-0.3.0a151.dist-info/METADATA
otpme-0.3.0a151.dist-info/WHEEL
otpme-0.3.0a151.dist-info/entry_points.txt
otpme-0.3.0a151.dist-info/top_level.txt
otpme-0.3.0a151.dist-info/RECORD
