Metadata-Version: 2.4
Name: otpme
Version: 0.3.0a151
Summary: OTPme: A flexible One-Time-Password system
Author-email: The2nd <the2nd@otpme.org>
Maintainer-email: The2nd <the2nd@otpme.org>
License: GNU GENERAL PUBLIC LICENSE
Project-URL: Homepage, https://www.otpme.org/redmine
Project-URL: Repository, https://github.com/the2nd/otpme.git
Project-URL: Issues, https://github.com/the2nd/otpme/issues
Keywords: OTP, U2F, fido2, two factor authentication, PAM, LDAP
Classifier: Development Status :: 3 - Alpha
Classifier: Programming Language :: Python :: 3
License-File: LICENSE
Requires-Dist: service_identity
Requires-Dist: importlib-metadata
Requires-Dist: ipaddr>=2.1.10
Requires-Dist: psutil>=5.5.1
Requires-Dist: pytz>=2019.3
Requires-Dist: pexpect>=4.6.0
Requires-Dist: pycryptodomex>=3.7.3
Requires-Dist: cryptography>=44.0.0
Requires-Dist: pyOpenSSL>=24.3.0
Requires-Dist: pysodium>=0.7.10
Requires-Dist: pylibacl>=0.5.1
Requires-Dist: ecdsa>=0.10
Requires-Dist: dnspython>=1.15.0
Requires-Dist: Twisted>=24.3.0
Requires-Dist: progressbar>=2.3
Requires-Dist: passlib>=1.7.2
Requires-Dist: netifaces>=0.8
Requires-Dist: prettytable>=0.7.2
Requires-Dist: setproctitle>=1.1.10
Requires-Dist: paramiko>=3.5.0
Requires-Dist: arprequest>=0.3
Requires-Dist: scapy>=2.4.4
Requires-Dist: Cython>=0.20
Requires-Dist: faust-cchardet>=2.1.19
Requires-Dist: chardet>=3.0.4
Requires-Dist: argon2>=0.1.10
Requires-Dist: future>=0.15.2
Requires-Dist: Cython>=0.29.36
Requires-Dist: PyJWT==1.7.1
Requires-Dist: fido2>=1.2.0
Requires-Dist: qrcode>=5.1
Requires-Dist: bson>=0.5.10
Requires-Dist: ujson>=5.7.0
Requires-Dist: orjson>=3.11.0
Requires-Dist: pysimdjson>=6.0.2
Requires-Dist: ldaptor>=21.2.0
Requires-Dist: humanize>=0.5.1
Requires-Dist: cachetools==5.3.1
Requires-Dist: posix-ipc>=1.0.5
Requires-Dist: tinydb>=4.5.2
Requires-Dist: psycopg2>=2.8.6
Requires-Dist: SQLAlchemy>=2.0.15
Requires-Dist: SQLAlchemy-Utils>=0.36.8
Requires-Dist: python-magic>=0.4.15
Requires-Dist: colorlog>=4.1.0
Requires-Dist: redis>=3.3.11
Requires-Dist: pylibmc>=1.6.3
Requires-Dist: python-yubico>=1.3.3
Requires-Dist: pyscard>=2.2.0
Requires-Dist: daemonize>=2.4.7
Requires-Dist: dogpile.cache>=0.9.0
Requires-Dist: ldap3>=2.4.1
Requires-Dist: pycryptodome>=3.4.3
Requires-Dist: PyQRCode>=1.2.1
Requires-Dist: pyotp>=2.8.0
Requires-Dist: pyre2>=0.3.6
Requires-Dist: lz4>=4.3.2
Requires-Dist: termcolor>=1.1.0
Requires-Dist: radius-eap-mschapv2-client>=1.0.6
Requires-Dist: pyrad>=2.4
Requires-Dist: Flask>=3.0.3
Requires-Dist: Flask-Login>=0.6.3
Requires-Dist: Flask-WTF>=1.2.1
Requires-Dist: gunicorn>=23.0.0
Requires-Dist: binaryornot>=0.4.4
Requires-Dist: cymysql>=1.0.1
Requires-Dist: yubikey-manager>=5.5.1
Requires-Dist: python-gnupg>=0.4.9
Requires-Dist: mfusepy>=3.0.0
Requires-Dist: xattr>=1.2.0
Requires-Dist: tlssysloghandler>=1.0.3
Requires-Dist: relppy>=0.4
Requires-Dist: strongtyping
Dynamic: license-file
